Workbook

Sheet Leia-me
A1: Apêndice C1 — Pesquisa de maturidade de IA por unidade
A2: Grupo Meridiano · Pesquisa aplicada de 08 a 25/09/2026 · consolidada em 30/09/2026
A4: O que é
A5: Pesquisa interna de autoavaliação da maturidade em IA das cinco unidades do grupo, conduzida pela área de Planejamento Estratégico a pedido do conselho, como insumo para o novo Head de IA. O questionário foi enviado às lideranças (diretores e gerentes) e às equipes que trabalham com dados, tecnologia e processos de cada unidade. As respostas são anônimas e não foram auditadas: representam a percepção de quem respondeu.
A7: Referencial
A8: O questionário foi elaborado com base no AI Maturity Framework publicado pela Element AI em 2020, que organiza a maturidade organizacional em IA em cinco dimensões (estratégia, dados, tecnologia, pessoas e governança) e cinco estágios (exploração, experimentação, formalização, otimização e transformação). As 20 afirmações e as descrições de cada estágio foram adaptadas pela empresa à sua realidade.
A10: Como foi respondido
A11: Para cada afirmação, o respondente escolheu o estágio (1 a 5) que melhor descreve a situação atual da sua própria unidade, com base nas descrições da aba Escala. Cada unidade avaliou apenas a si mesma.
A12: Ao final, havia três perguntas complementares: como as iniciativas de IA deveriam ser organizadas no grupo, uso de ferramentas de IA não fornecidas pela empresa e um campo aberto para comentários.
A14: Abas
A15: Escala: descrição dos cinco estágios em cada dimensão e faixas usadas para classificar as médias.
A16: Questionário: as 20 afirmações, quatro por dimensão.
... A36: Referencial: Element AI, AI Maturity Framework (2020), dimensões e estágios conforme divulgação pública do framework. Respostas: pesquisa interna, set/2026.

Sheet Escala
A1: Escala de maturidade — descrição dos estágios por dimensão
A3: Dimensão | B3: 1. Exploração | C3: 2. Experimentação | D3: 3. Formalização | E3: 4. Otimização | F3: 5. Transformação
A4: Estratégia | B4: IA é tema de interesse, sem objetivos nem patrocínio definidos. | C4: Iniciativas pontuais, puxadas por pessoas ou áreas, sem critério comum de priorização. | D4: Há objetivos de IA ligados às metas da unidade, orçamento e patrocinador identificados. | E4: Portfólio de IA gerido por valor, com metas de negócio acompanhadas e revisão periódica. | F4: IA orienta a estratégia e os modelos de negócio da unidade.
A5: Dados | B5: Dados dispersos, de difícil acesso e qualidade desconhecida. | C5: Dados reunidos projeto a projeto, com tratamento manual. | D5: Principais dados acessíveis, com responsáveis e definições documentadas. | E5: Qualidade medida continuamente; dados compartilhados entre áreas por padrões comuns. | F5: Dados tratados como ativo do negócio, reutilizados em escala em toda a empresa.
A6: Tecnologia | B6: Sem ferramentas ou ambientes próprios para IA. | C6: Ferramentas escolhidas por projeto; implantação manual e caso a caso. | D6: Ambientes e práticas padronizados para levar soluções à produção. | E6: Plataforma comum com implantação, monitoramento e controle de custos automatizados. | F6: Plataforma permite criar e escalar novas soluções de IA rapidamente e com segurança.
A7: Pessoas | B7: Conhecimento de IA restrito a poucos interessados. | C7: Pequenos grupos técnicos ou fornecedores concentram o conhecimento. | D7: Papéis técnicos definidos; áreas de negócio participam das iniciativas. | E7: Capacitação contínua; negócio e tecnologia trabalham em times integrados. | F7: Cultura de uso de IA difundida em toda a unidade.
A8: Governança | B8: Sem regras sobre o uso de IA. | C8: Regras informais, aplicadas caso a caso por cada time. | D8: Políticas e responsáveis definidos; riscos avaliados antes da entrada em produção. | E8: Controles aplicados de forma contínua (monitoramento, auditoria, revisão humana, registro). | F8: Governança integrada ao ciclo de vida de todas as soluções e revisada periodicamente.
A11: Faixas de classificação das médias
A12: A partir de | B12: Estágio
A13: 1 | B13: Exploração
A14: 2 | B14: Experimentação
A15: 3 | B15: Formalização
A16: 4 | B16: Otimização
A17: 5 | B17: Transformação
A19: Exemplo: média de 2,6 = Experimentação; média de 3,0 = Formalização.

Sheet Questionário
A1: Questionário — afirmações avaliadas (escala de 1 a 5, conforme aba Escala)
A3: ID | B3: Dimensão | C3: Afirmação
A4: E1 | B4: Estratégia | C4: Existe uma visão clara de como a IA contribui para os objetivos da unidade.
A5: E2 | B5: Estratégia | C5: As iniciativas de IA são priorizadas com critérios explícitos de valor de negócio.
A6: E3 | B6: Estratégia | C6: Há orçamento e patrocínio definidos para IA além do ciclo de cada projeto.
A7: E4 | B7: Estratégia | C7: Os resultados das iniciativas de IA são medidos contra metas de negócio.
A8: D1 | B8: Dados | C8: Os dados necessários às iniciativas de IA estão disponíveis e acessíveis.
A9: D2 | B9: Dados | C9: A qualidade dos dados é medida e há responsáveis por corrigi-la.
A10: D3 | B10: Dados | C10: Os principais dados têm definições comuns documentadas (dono, origem, significado).
A11: D4 | B11: Dados | C11: Os dados podem ser compartilhados com outras unidades de forma ágil e segura.
A12: T1 | B12: Tecnologia | C12: A unidade tem ferramentas e infraestrutura adequadas para construir soluções de IA.
A13: T2 | B13: Tecnologia | C13: Soluções de IA passam do piloto à produção de forma padronizada (implantação, testes, versionamento).
A14: T3 | B14: Tecnologia | C14: Modelos e agentes em produção são monitorados (desempenho, qualidade das respostas, custo).
... A23: G4 | B23: Governança | C23: Decisões automatizadas têm revisão humana, registro e canal de contestação quando necessário.
A25: Perguntas complementares
A26: C1 · Como as iniciativas de IA deveriam ser organizadas no grupo? (uma opção; ver aba Organização da IA)
A27: C2 · Com que frequência você usa, no trabalho, ferramentas de IA não fornecidas pela empresa? (frequentemente, às vezes, nunca)
A28: C3 · Se usa, já inseriu nessas ferramentas dados de clientes ou de colaboradores? (sim, não)
A29: C4 · Comentários livres sobre IA na sua unidade (opcional).

Sheet Participação
A1: Participação na pesquisa
A2: Liderança: diretores e gerentes. Equipes: coordenadores, especialistas e analistas que trabalham com dados, tecnologia e processos.
A4: Unidade | B4: Liderança — convidados | C4: Liderança — respondentes | D4: Liderança — taxa de resposta | E4: Equipes — convidados | F4: Equipes — respondentes | G4: Equipes — taxa de resposta | H4: Total de respondentes | I4: Taxa de resposta total
A5: Marketplace e e-commerce | B5: 12 | C5: 10 | D5: =IF(B5=0,0,C5/B5) -> 0.83333333 | E5: 85 | F5: 60 | G5: =IF(E5=0,0,F5/E5) -> 0.70588235 | H5: =C5+F5 -> 70 | I5: =IF(B5+E5=0,0,H5/(B5+E5)) -> 0.72164948
A6: Logística | B6: 10 | C6: 8 | D6: =IF(B6=0,0,C6/B6) -> 0.8 | E6: 60 | F6: 31 | G6: =IF(E6=0,0,F6/E6) -> 0.51666667 | H6: =C6+F6 -> 39 | I6: =IF(B6+E6=0,0,H6/(B6+E6)) -> 0.55714286
A7: Lojas físicas | B7: 40 | C7: 22 | D7: =IF(B7=0,0,C7/B7) -> 0.55 | E7: 150 | F7: 27 | G7: =IF(E7=0,0,F7/E7) -> 0.18 | H7: =C7+F7 -> 49 | I7: =IF(B7+E7=0,0,H7/(B7+E7)) -> 0.25789474
A8: Serviços financeiros | B8: 8 | C8: 7 | D8: =IF(B8=0,0,C8/B8) -> 0.875 | E8: 45 | F8: 33 | G8: =IF(E8=0,0,F8/E8) -> 0.73333333 | H8: =C8+F8 -> 40 | I8: =IF(B8+E8=0,0,H8/(B8+E8)) -> 0.75471698
A9: Corporativo | B9: 15 | C9: 11 | D9: =IF(B9=0,0,C9/B9) -> 0.73333333 | E9: 70 | F9: 38 | G9: =IF(E9=0,0,F9/E9) -> 0.54285714 | H9: =C9+F9 -> 49 | I9: =IF(B9+E9=0,0,H9/(B9+E9)) -> 0.57647059
A10: Total | B10: =SUM(B5:B9) -> 85 | C10: =SUM(C5:C9) -> 58 | D10: =IF(B10=0,0,C10/B10) -> 0.68235294 | E10: =SUM(E5:E9) -> 410 | F10: =SUM(F5:F9) -> 189 | G10: =IF(E10=0,0,F10/E10) -> 0.46097561 | H10: =SUM(H5:H9) -> 247 | I10: =IF(B10+E10=0,0,H10/(B10+E10)) -> 0.4989899
A12: Nas Lojas físicas, o convite às equipes incluiu uma amostra de coordenadores de loja, além dos analistas de operações.

Sheet Respostas
A1: Respostas — média das notas por afirmação (1 a 5)
A2: Liderança = diretores e gerentes; Equipes = demais respondentes. Cada unidade avaliou a si mesma.
A4: ID | B4: Dimensão | C4: Marketplace e e-commerce | E4: Logística | G4: Lojas físicas | I4: Serviços financeiros | K4: Corporativo
C5: Liderança | D5: Equipes | E5: Liderança | F5: Equipes | G5: Liderança | H5: Equipes | I5: Liderança | J5: Equipes | K5: Liderança | L5: Equipes
A6: E1 | B6: Estratégia | C6: 3.6 | D6: 2.9 | E6: 3 | F6: 2.2 | G6: 1.6 | H6: 1.9 | I6: 3.4 | J6: 2.8 | K6: 2.6 | L6: 2
A7: E2 | B7: Estratégia | C7: 3.2 | D7: 2.4 | E7: 2.4 | F7: 1.9 | G7: 1.4 | H7: 1.5 | I7: 3.2 | J7: 2.9 | K7: 2.4 | L7: 1.8
A8: E3 | B8: Estratégia | C8: 3 | D8: 2.6 | E8: 1.8 | F8: 1.7 | G8: 1.2 | H8: 1.3 | I8: 3 | J8: 2.6 | K8: 2 | L8: 1.7
A9: E4 | B9: Estratégia | C9: 2.8 | D9: 2.2 | E9: 2.6 | F9: 2 | G9: 1.3 | H9: 1.4 | I9: 3.3 | J9: 2.7 | K9: 2 | L9: 1.6
A10: D1 | B10: Dados | C10: 4.2 | D10: 3.9 | E10: 3.8 | F10: 3.6 | G10: 2 | H10: 1.8 | I10: 4 | J10: 3.7 | K10: 2.8 | L10: 2.5
A11: D2 | B11: Dados | C11: 3.8 | D11: 3.1 | E11: 3.4 | F11: 3.2 | G11: 1.8 | H11: 1.6 | I11: 3.8 | J11: 3.4 | K11: 2.4 | L11: 2.2
A12: D3 | B12: Dados | C12: 3.6 | D12: 2.8 | E12: 3 | F12: 2.8 | G12: 1.5 | H12: 1.4 | I12: 3.6 | J12: 3.2 | K12: 2.2 | L12: 2
A13: D4 | B13: Dados | C13: 3.4 | D13: 2.5 | E13: 2.6 | F13: 2.4 | G13: 1.6 | H13: 1.5 | I13: 3 | J13: 2.6 | K13: 2.6 | L13: 2
A14: T1 | B14: Tecnologia | C14: 4.4 | D14: 4.3 | E14: 3.9 | F14: 3 | G14: 1.4 | H14: 2.6 | I14: 3.4 | J14: 3 | K14: 3.6 | L14: 3.2
A15: T2 | B15: Tecnologia | C15: 4 | D15: 2.9 | E15: 3.2 | F15: 2.1 | G15: 1.2 | H15: 1.8 | I15: 3 | J15: 2.6 | K15: 3.2 | L15: 2.6
A16: T3 | B16: Tecnologia | C16: 3.8 | D16: 2.4 | E16: 2.8 | F16: 1.7 | G16: 1.1 | H16: 1.3 | I16: 3.2 | J16: 2.2 | K16: 3 | L16: 2.4
A17: T4 | B17: Tecnologia | C17: 3.9 | D17: 3 | E17: 3.4 | F17: 2 | G17: 1.6 | H17: 1.5 | I17: 3.4 | J17: 3.1 | K17: 3.8 | L17: 3.4
... A25: G4 | B25: Governança | C25: 3.4 | D25: 2.1 | E25: 2.3 | F25: 1.6 | G25: 1.3 | H25: 1.2 | I25: 4 | J25: 2.1 | K25: 2.6 | L25: 2.2
B26: Respondentes | C26: =Participação!C5 -> 10 | D26: =Participação!F5 -> 60 | E26: =Participação!C6 -> 8 | F26: =Participação!F6 -> 31 | G26: =Participação!C7 -> 22 | H26: =Participação!F7 -> 27 | I26: =Participação!C8 -> 7 | J26: =Participação!F8 -> 33 | K26: =Participação!C9 -> 11 | L26: =Participação!F9 -> 38

Sheet Autoavaliação
A1: Autoavaliação — maturidade percebida por unidade e dimensão
A2: Médias de 1 a 5. Diferença = liderança − equipes. Resultados da percepção dos respondentes; não substituem um diagnóstico com base em evidências.
A4: Média da liderança
A5: Unidade | B5: Estratégia | C5: Dados | D5: Tecnologia | E5: Pessoas | F5: Governança | G5: Geral
A6: Marketplace e e-commerce | B6: =AVERAGE(Respostas!C6:C9) -> 3.15 | C6: =AVERAGE(Respostas!C10:C13) -> 3.75 | D6: =AVERAGE(Respostas!C14:C17) -> 4.025 | E6: =AVERAGE(Respostas!C18:C21) -> 3.6 | F6: =AVERAGE(Respostas!C22:C25) -> 3.575 | G6: =AVERAGE(B6:F6) -> 3.62
A7: Logística | B7: =AVERAGE(Respostas!E6:E9) -> 2.45 | C7: =AVERAGE(Respostas!E10:E13) -> 3.2 | D7: =AVERAGE(Respostas!E14:E17) -> 3.325 | E7: =AVERAGE(Respostas!E18:E21) -> 2.1 | F7: =AVERAGE(Respostas!E22:E25) -> 2.375 | G7: =AVERAGE(B7:F7) -> 2.69
A8: Lojas físicas | B8: =AVERAGE(Respostas!G6:G9) -> 1.375 | C8: =AVERAGE(Respostas!G10:G13) -> 1.725 | D8: =AVERAGE(Respostas!G14:G17) -> 1.325 | E8: =AVERAGE(Respostas!G18:G21) -> 1.525 | F8: =AVERAGE(Respostas!G22:G25) -> 1.5 | G8: =AVERAGE(B8:F8) -> 1.49
A9: Serviços financeiros | B9: =AVERAGE(Respostas!I6:I9) -> 3.225 | C9: =AVERAGE(Respostas!I10:I13) -> 3.6 | D9: =AVERAGE(Respostas!I14:I17) -> 3.25 | E9: =AVERAGE(Respostas!I18:I21) -> 2.75 | F9: =AVERAGE(Respostas!I22:I25) -> 4.15 | G9: =AVERAGE(B9:F9) -> 3.395
A10: Corporativo | B10: =AVERAGE(Respostas!K6:K9) -> 2.25 | C10: =AVERAGE(Respostas!K10:K13) -> 2.5 | D10: =AVERAGE(Respostas!K14:K17) -> 3.4 | E10: =AVERAGE(Respostas!K18:K21) -> 2.5 | F10: =AVERAGE(Respostas!K22:K25) -> 2.75 | G10: =AVERAGE(B10:F10) -> 2.68
A12: Média das equipes
A13: Unidade | B13: Estratégia | C13: Dados | D13: Tecnologia | E13: Pessoas | F13: Governança | G13: Geral
A14: Marketplace e e-commerce | B14: =AVERAGE(Respostas!D6:D9) -> 2.525 | C14: =AVERAGE(Respostas!D10:D13) -> 3.075 | D14: =AVERAGE(Respostas!D14:D17) -> 3.15 | E14: =AVERAGE(Respostas!D18:D21) -> 3.025 | F14: =AVERAGE(Respostas!D22:D25) -> 2.2 | G14: =AVERAGE(B14:F14) -> 2.795
A15: Logística | B15: =AVERAGE(Respostas!F6:F9) -> 1.95 | C15: =AVERAGE(Respostas!F10:F13) -> 3 | D15: =AVERAGE(Respostas!F14:F17) -> 2.2 | E15: =AVERAGE(Respostas!F18:F21) -> 1.8 | F15: =AVERAGE(Respostas!F22:F25) -> 1.7 | G15: =AVERAGE(B15:F15) -> 2.13
A16: Lojas físicas | B16: =AVERAGE(Respostas!H6:H9) -> 1.525 | C16: =AVERAGE(Respostas!H10:H13) -> 1.575 | D16: =AVERAGE(Respostas!H14:H17) -> 1.8 | E16: =AVERAGE(Respostas!H18:H21) -> 2.075 | F16: =AVERAGE(Respostas!H22:H25) -> 1.275 | G16: =AVERAGE(B16:F16) -> 1.65
A17: Serviços financeiros | B17: =AVERAGE(Respostas!J6:J9) -> 2.75 | C17: =AVERAGE(Respostas!J10:J13) -> 3.225 | D17: =AVERAGE(Respostas!J14:J17) -> 2.725 | E17: =AVERAGE(Respostas!J18:J21) -> 2.45 | F17: =AVERAGE(Respostas!J22:J25) -> 2.725 | G17: =AVERAGE(B17:F17) -> 2.775
A18: Corporativo | B18: =AVERAGE(Respostas!L6:L9) -> 1.775 | C18: =AVERAGE(Respostas!L10:L13) -> 2.175 | D18: =AVERAGE(Respostas!L14:L17) -> 2.9 | E18: =AVERAGE(Respostas!L18:L21) -> 2.275 | F18: =AVERAGE(Respostas!L22:L25) -> 2.25 | G18: =AVERAGE(B18:F18) -> 2.275
A20: Diferença de percepção (liderança − equipes)
A21: Unidade | B21: Estratégia | C21: Dados | D21: Tecnologia | E21: Pessoas | F21: Governança | G21: Geral
A22: Marketplace e e-commerce | B22: =B6-B14 -> 0.625 | C22: =C6-C14 -> 0.675 | D22: =D6-D14 -> 0.875 | E22: =E6-E14 -> 0.575 | F22: =F6-F14 -> 1.375 | G22: =G6-G14 -> 0.825
A23: Logística | B23: =B7-B15 -> 0.5 | C23: =C7-C15 -> 0.2 | D23: =D7-D15 -> 1.125 | E23: =E7-E15 -> 0.3 | F23: =F7-F15 -> 0.675 | G23: =G7-G15 -> 0.56
A24: Lojas físicas | B24: =B8-B16 -> -0.15 | C24: =C8-C16 -> 0.15 | D24: =D8-D16 -> -0.475 | E24: =E8-E16 -> -0.55 | F24: =F8-F16 -> 0.225 | G24: =G8-G16 -> -0.16
A25: Serviços financeiros | B25: =B9-B17 -> 0.475 | C25: =C9-C17 -> 0.375 | D25: =D9-D17 -> 0.525 | E25: =E9-E17 -> 0.3 | F25: =F9-F17 -> 1.425 | G25: =G9-G17 -> 0.62
A26: Corporativo | B26: =B10-B18 -> 0.475 | C26: =C10-C18 -> 0.325 | D26: =D10-D18 -> 0.5 | E26: =E10-E18 -> 0.225 | F26: =F10-F18 -> 0.5 | G26: =G10-G18 -> 0.405
A28: Média das duas visões (liderança e equipes)
A29: Unidade | B29: Estratégia | C29: Dados | D29: Tecnologia | E29: Pessoas | F29: Governança
A30: Marketplace e e-commerce | B30: =AVERAGE(B6,B14) -> 2.8375 | C30: =AVERAGE(C6,C14) -> 3.4125 | D30: =AVERAGE(D6,D14) -> 3.5875 | E30: =AVERAGE(E6,E14) -> 3.3125 | F30: =AVERAGE(F6,F14) -> 2.8875
A31: Logística | B31: =AVERAGE(B7,B15) -> 2.2 | C31: =AVERAGE(C7,C15) -> 3.1 | D31: =AVERAGE(D7,D15) -> 2.7625 | E31: =AVERAGE(E7,E15) -> 1.95 | F31: =AVERAGE(F7,F15) -> 2.0375
A32: Lojas físicas | B32: =AVERAGE(B8,B16) -> 1.45 | C32: =AVERAGE(C8,C16) -> 1.65 | D32: =AVERAGE(D8,D16) -> 1.5625 | E32: =AVERAGE(E8,E16) -> 1.8 | F32: =AVERAGE(F8,F16) -> 1.3875
A33: Serviços financeiros | B33: =AVERAGE(B9,B17) -> 2.9875 | C33: =AVERAGE(C9,C17) -> 3.4125 | D33: =AVERAGE(D9,D17) -> 2.9875 | E33: =AVERAGE(E9,E17) -> 2.6 | F33: =AVERAGE(F9,F17) -> 3.4375
A34: Corporativo | B34: =AVERAGE(B10,B18) -> 2.0125 | C34: =AVERAGE(C10,C18) -> 2.3375 | D34: =AVERAGE(D10,D18) -> 3.15 | E34: =AVERAGE(E10,E18) -> 2.3875 | F34: =AVERAGE(F10,F18) -> 2.5
A36: Estágio segundo a autoavaliação
A37: Unidade | B37: Estratégia | C37: Dados | D37: Tecnologia | E37: Pessoas | F37: Governança
A38: Marketplace e e-commerce | B38: =LOOKUP(ROUND(B30,1),Escala!$A$13:$A$17,Escala!$B$13:$B$17) -> Experimentação | C38: =LOOKUP(ROUND(C30,1),Escala!$A$13:$A$17,Escala!$B$13:$B$17) -> Formalização | D38: =LOOKUP(ROUND(D30,1),Escala!$A$13:$A$17,Escala!$B$13:$B$17) -> Formalização | E38: =LOOKUP(ROUND(E30,1),Escala!$A$13:$A$17,Escala!$B$13:$B$17) -> Formalização | F38: =LOOKUP(ROUND(F30,1),Escala!$A$13:$A$17,Escala!$B$13:$B$17) -> Experimentação
A39: Logística | B39: =LOOKUP(ROUND(B31,1),Escala!$A$13:$A$17,Escala!$B$13:$B$17) -> Experimentação | C39: =LOOKUP(ROUND(C31,1),Escala!$A$13:$A$17,Escala!$B$13:$B$17) -> Formalização | D39: =LOOKUP(ROUND(D31,1),Escala!$A$13:$A$17,Escala!$B$13:$B$17) -> Experimentação | E39: =LOOKUP(ROUND(E31,1),Escala!$A$13:$A$17,Escala!$B$13:$B$17) -> Experimentação | F39: =LOOKUP(ROUND(F31,1),Escala!$A$13:$A$17,Escala!$B$13:$B$17) -> Experimentação
A40: Lojas físicas | B40: =LOOKUP(ROUND(B32,1),Escala!$A$13:$A$17,Escala!$B$13:$B$17) -> Exploração | C40: =LOOKUP(ROUND(C32,1),Escala!$A$13:$A$17,Escala!$B$13:$B$17) -> Exploração | D40: =LOOKUP(ROUND(D32,1),Escala!$A$13:$A$17,Escala!$B$13:$B$17) -> Exploração | E40: =LOOKUP(ROUND(E32,1),Escala!$A$13:$A$17,Escala!$B$13:$B$17) -> Exploração | F40: =LOOKUP(ROUND(F32,1),Escala!$A$13:$A$17,Escala!$B$13:$B$17) -> Exploração
A41: Serviços financeiros | B41: =LOOKUP(ROUND(B33,1),Escala!$A$13:$A$17,Escala!$B$13:$B$17) -> Formalização | C41: =LOOKUP(ROUND(C33,1),Escala!$A$13:$A$17,Escala!$B$13:$B$17) -> Formalização | D41: =LOOKUP(ROUND(D33,1),Escala!$A$13:$A$17,Escala!$B$13:$B$17) -> Formalização | E41: =LOOKUP(ROUND(E33,1),Escala!$A$13:$A$17,Escala!$B$13:$B$17) -> Experimentação | F41: =LOOKUP(ROUND(F33,1),Escala!$A$13:$A$17,Escala!$B$13:$B$17) -> Formalização
A42: Corporativo | B42: =LOOKUP(ROUND(B34,1),Escala!$A$13:$A$17,Escala!$B$13:$B$17) -> Experimentação | C42: =LOOKUP(ROUND(C34,1),Escala!$A$13:$A$17,Escala!$B$13:$B$17) -> Experimentação | D42: =LOOKUP(ROUND(D34,1),Escala!$A$13:$A$17,Escala!$B$13:$B$17) -> Formalização | E42: =LOOKUP(ROUND(E34,1),Escala!$A$13:$A$17,Escala!$B$13:$B$17) -> Experimentação | F42: =LOOKUP(ROUND(F34,1),Escala!$A$13:$A$17,Escala!$B$13:$B$17) -> Experimentação

Sheet Organização da IA
A1: Pergunta C1 — Como as iniciativas de IA deveriam ser organizadas no grupo?
A2: Número de respondentes que escolheu cada opção (uma por respondente).
A4: A. Uma área corporativa concentra o desenvolvimento e a operação de todas as soluções de IA
A5: B. Uma área central define padrões, plataforma e regras; as unidades desenvolvem suas próprias soluções
A6: C. Cada unidade decide e desenvolve suas soluções com autonomia, com coordenação mínima entre elas
A7: D. Não sei / sem opinião
A9: Unidade | B9: Grupo | C9: Respondentes | D9: A | E9: B | F9: C | G9: D | H9: % A | I9: % B | J9: % C | K9: % D
A10: Marketplace e e-commerce | B10: Liderança | C10: =SUM(D10:G10) -> 10 | D10: 1 | E10: 3 | F10: 6 | G10: 0 | H10: =IF($C10=0,0,D10/$C10) -> 0.1 | I10: =IF($C10=0,0,E10/$C10) -> 0.3 | J10: =IF($C10=0,0,F10/$C10) -> 0.6 | K10: =IF($C10=0,0,G10/$C10) -> 0
A11: Marketplace e e-commerce | B11: Equipes | C11: =SUM(D11:G11) -> 60 | D11: 6 | E11: 24 | F11: 27 | G11: 3 | H11: =IF($C11=0,0,D11/$C11) -> 0.1 | I11: =IF($C11=0,0,E11/$C11) -> 0.4 | J11: =IF($C11=0,0,F11/$C11) -> 0.45 | K11: =IF($C11=0,0,G11/$C11) -> 0.05
A12: Logística | B12: Liderança | C12: =SUM(D12:G12) -> 8 | D12: 2 | E12: 5 | F12: 1 | G12: 0 | H12: =IF($C12=0,0,D12/$C12) -> 0.25 | I12: =IF($C12=0,0,E12/$C12) -> 0.625 | J12: =IF($C12=0,0,F12/$C12) -> 0.125 | K12: =IF($C12=0,0,G12/$C12) -> 0
A13: Logística | B13: Equipes | C13: =SUM(D13:G13) -> 31 | D13: 5 | E13: 14 | F13: 4 | G13: 8 | H13: =IF($C13=0,0,D13/$C13) -> 0.16129032 | I13: =IF($C13=0,0,E13/$C13) -> 0.4516129 | J13: =IF($C13=0,0,F13/$C13) -> 0.12903226 | K13: =IF($C13=0,0,G13/$C13) -> 0.25806452
A14: Lojas físicas | B14: Liderança | C14: =SUM(D14:G14) -> 22 | D14: 12 | E14: 6 | F14: 1 | G14: 3 | H14: =IF($C14=0,0,D14/$C14) -> 0.54545455 | I14: =IF($C14=0,0,E14/$C14) -> 0.27272727 | J14: =IF($C14=0,0,F14/$C14) -> 0.045454545 | K14: =IF($C14=0,0,G14/$C14) -> 0.13636364
A15: Lojas físicas | B15: Equipes | C15: =SUM(D15:G15) -> 27 | D15: 6 | E15: 5 | F15: 9 | G15: 7 | H15: =IF($C15=0,0,D15/$C15) -> 0.22222222 | I15: =IF($C15=0,0,E15/$C15) -> 0.18518519 | J15: =IF($C15=0,0,F15/$C15) -> 0.33333333 | K15: =IF($C15=0,0,G15/$C15) -> 0.25925926
A16: Serviços financeiros | B16: Liderança | C16: =SUM(D16:G16) -> 7 | D16: 1 | E16: 2 | F16: 4 | G16: 0 | H16: =IF($C16=0,0,D16/$C16) -> 0.14285714 | I16: =IF($C16=0,0,E16/$C16) -> 0.28571429 | J16: =IF($C16=0,0,F16/$C16) -> 0.57142857 | K16: =IF($C16=0,0,G16/$C16) -> 0
A17: Serviços financeiros | B17: Equipes | C17: =SUM(D17:G17) -> 33 | D17: 6 | E17: 15 | F17: 9 | G17: 3 | H17: =IF($C17=0,0,D17/$C17) -> 0.18181818 | I17: =IF($C17=0,0,E17/$C17) -> 0.45454545 | J17: =IF($C17=0,0,F17/$C17) -> 0.27272727 | K17: =IF($C17=0,0,G17/$C17) -> 0.090909091
A18: Corporativo | B18: Liderança | C18: =SUM(D18:G18) -> 11 | D18: 8 | E18: 2 | F18: 1 | G18: 0 | H18: =IF($C18=0,0,D18/$C18) -> 0.72727273 | I18: =IF($C18=0,0,E18/$C18) -> 0.18181818 | J18: =IF($C18=0,0,F18/$C18) -> 0.090909091 | K18: =IF($C18=0,0,G18/$C18) -> 0
A19: Corporativo | B19: Equipes | C19: =SUM(D19:G19) -> 38 | D19: 16 | E19: 12 | F19: 4 | G19: 6 | H19: =IF($C19=0,0,D19/$C19) -> 0.42105263 | I19: =IF($C19=0,0,E19/$C19) -> 0.31578947 | J19: =IF($C19=0,0,F19/$C19) -> 0.10526316 | K19: =IF($C19=0,0,G19/$C19) -> 0.15789474
A20: Total do grupo | B20: Liderança | C20: =SUMIF($B$10:$B$19,$B20,C$10:C$19) -> 58 | D20: =SUMIF($B$10:$B$19,$B20,D$10:D$19) -> 24 | E20: =SUMIF($B$10:$B$19,$B20,E$10:E$19) -> 18 | F20: =SUMIF($B$10:$B$19,$B20,F$10:F$19) -> 13 | G20: =SUMIF($B$10:$B$19,$B20,G$10:G$19) -> 3 | H20: =IF($C20=0,0,D20/$C20) -> 0.4137931 | I20: =IF($C20=0,0,E20/$C20) -> 0.31034483 | J20: =IF($C20=0,0,F20/$C20) -> 0.22413793 | K20: =IF($C20=0,0,G20/$C20) -> 0.051724138
A21: Total do grupo | B21: Equipes | C21: =SUMIF($B$10:$B$19,$B21,C$10:C$19) -> 189 | D21: =SUMIF($B$10:$B$19,$B21,D$10:D$19) -> 39 | E21: =SUMIF($B$10:$B$19,$B21,E$10:E$19) -> 70 | F21: =SUMIF($B$10:$B$19,$B21,F$10:F$19) -> 53 | G21: =SUMIF($B$10:$B$19,$B21,G$10:G$19) -> 27 | H21: =IF($C21=0,0,D21/$C21) -> 0.20634921 | I21: =IF($C21=0,0,E21/$C21) -> 0.37037037 | J21: =IF($C21=0,0,F21/$C21) -> 0.28042328 | K21: =IF($C21=0,0,G21/$C21) -> 0.14285714
A22: Total geral | C22: =C20+C21 -> 247 | D22: =D20+D21 -> 63 | E22: =E20+E21 -> 88 | F22: =F20+F21 -> 66 | G22: =G20+G21 -> 30 | H22: =IF($C22=0,0,D22/$C22) -> 0.25506073 | I22: =IF($C22=0,0,E22/$C22) -> 0.3562753 | J22: =IF($C22=0,0,F22/$C22) -> 0.26720648 | K22: =IF($C22=0,0,G22/$C22) -> 0.12145749

Sheet Ferramentas externas
A1: Perguntas C2 e C3 — Uso de ferramentas de IA não fornecidas pela empresa
A2: Todos os respondentes (liderança e equipes). C3 respondida apenas por quem usa essas ferramentas.
A4: Unidade | B4: Respondentes | C4: Usa frequentemente | D4: Usa às vezes | E4: Nunca usa | F4: % que usa | G4: Já inseriu dados de clientes ou colaboradores | H4: % dos usuários que inseriu dados
A5: Marketplace e e-commerce | B5: =SUM(C5:E5) -> 70 | C5: 22 | D5: 30 | E5: 18 | F5: =IF(B5=0,0,(C5+D5)/B5) -> 0.74285714 | G5: 9 | H5: =IF(C5+D5=0,0,G5/(C5+D5)) -> 0.17307692
A6: Logística | B6: =SUM(C6:E6) -> 39 | C6: 9 | D6: 14 | E6: 16 | F6: =IF(B6=0,0,(C6+D6)/B6) -> 0.58974359 | G6: 6 | H6: =IF(C6+D6=0,0,G6/(C6+D6)) -> 0.26086957
A7: Lojas físicas | B7: =SUM(C7:E7) -> 49 | C7: 14 | D7: 15 | E7: 20 | F7: =IF(B7=0,0,(C7+D7)/B7) -> 0.59183673 | G7: 11 | H7: =IF(C7+D7=0,0,G7/(C7+D7)) -> 0.37931034
A8: Serviços financeiros | B8: =SUM(C8:E8) -> 40 | C8: 5 | D8: 11 | E8: 24 | F8: =IF(B8=0,0,(C8+D8)/B8) -> 0.4 | G8: 2 | H8: =IF(C8+D8=0,0,G8/(C8+D8)) -> 0.125
A9: Corporativo | B9: =SUM(C9:E9) -> 49 | C9: 13 | D9: 17 | E9: 19 | F9: =IF(B9=0,0,(C9+D9)/B9) -> 0.6122449 | G9: 8 | H9: =IF(C9+D9=0,0,G9/(C9+D9)) -> 0.26666667
A10: Total | B10: =SUM(B5:B9) -> 247 | C10: =SUM(C5:C9) -> 63 | D10: =SUM(D5:D9) -> 87 | E10: =SUM(E5:E9) -> 97 | F10: =IF(B10=0,0,(C10+D10)/B10) -> 0.60728745 | G10: =SUM(G5:G9) -> 36 | H10: =IF(C10+D10=0,0,G10/(C10+D10)) -> 0.24
A12: Conferência: o total de respondentes de cada unidade deve coincidir com a aba Participação.
A13: Unidade | B13: Respondentes (Participação) | C13: Confere?
A14: =A5 -> Marketplace e e-commerce | B14: =Participação!H5 -> 70 | C14: =IF(B14=B5,"Sim","Não") -> Sim
A15: =A6 -> Logística | B15: =Participação!H6 -> 39 | C15: =IF(B15=B6,"Sim","Não") -> Sim
A16: =A7 -> Lojas físicas | B16: =Participação!H7 -> 49 | C16: =IF(B16=B7,"Sim","Não") -> Sim
A17: =A8 -> Serviços financeiros | B17: =Participação!H8 -> 40 | C17: =IF(B17=B8,"Sim","Não") -> Sim
A18: =A9 -> Corporativo | B18: =Participação!H9 -> 49 | C18: =IF(B18=B9,"Sim","Não") -> Sim

Sheet Comentários
A1: Pergunta C4 — Seleção de comentários livres das equipes
A2: Transcritos sem edição de conteúdo. Respondentes identificados apenas por unidade e cargo. A visão das lideranças está nas entrevistas (Apêndice C2).
A4: # | B4: Unidade | C4: Cargo | D4: Comentário
A5: 1 | B5: Marketplace e e-commerce | C5: Cientista de dados | D5: Colocamos coisas em produção rápido, mas ninguém mede se as respostas do agente estão certas. O teste antes de lançar foi uma lista de perguntas que nós mesmos escrevemos.
A6: 2 | B6: Marketplace e e-commerce | C6: Engenheiro de dados | D6: Cada time sobe seus ambientes na Nuvem A para testar e muita coisa fica ligada depois que o teste acaba. Não existe um dono para limpar.
A7: 3 | B7: Marketplace e e-commerce | C7: Analista de CRM | D7: Não temos certeza de quais clientes antigos autorizaram receber e-mail. A campanha sai para toda a base selecionada pelo modelo.
A8: 4 | B8: Logística | C8: Analista de logística | D8: Só a consultoria sabe mexer no fluxo da plataforma W. Se algo para de funcionar à noite, não temos a quem recorrer.
A9: 5 | B9: Logística | C9: Coordenador de CD | D9: Os dados de rastreamento são bons. O problema é que cada transportadora manda num formato e alguém precisa juntar tudo na mão.
A10: 6 | B10: Lojas físicas | C10: Coordenador de operações regionais | D10: As lojas já usam IA por conta própria, porque nada oficial chegou até nós. É melhor ter uma ferramenta aprovada do que fingir que ninguém usa.
A11: 7 | B11: Lojas físicas | C11: Analista de operações | D11: Montar a escala em planilha levava um dia por loja; com o app que fizemos, leva minutos. Gerentes de outras regiões já pediram acesso.
A12: 8 | B12: Lojas físicas | C12: Coordenador de loja | D12: Nunca recebi orientação sobre o que pode ou não pode ser colocado nessas ferramentas de IA.
A13: 9 | B13: Serviços financeiros | C13: Analista de risco | D13: O modelo não foi reavaliado desde o lançamento. Quando um seller recusado liga, ninguém consegue explicar o motivo da recusa.
A14: 10 | B14: Corporativo | C14: Analista de controladoria | D14: Não conseguimos dizer quanto cada iniciativa de IA custa nem quanto retorna. Os gastos estão espalhados em contas de várias áreas.
A15: 11 | B15: Corporativo | C15: Analista de RH | D15: O assistente de RH ajuda no dia a dia, mas os colaboradores perguntam se as conversas ficam gravadas e quem tem acesso a elas.

Sheet Gráficos
A1: Gráficos (dados da aba Autoavaliação)
